pymoq/__init__.py
pymoq/_modidx.py
pymoq/all.py
pymoq/argument_validators.py
pymoq/core.py
pymoq/return_value_generators.py
pymoq/signature_validators.py
pymoq/mocking/__init__.py
pymoq/mocking/functions.py
pymoq/mocking/objects.py
moqpy-0.0.2.dist-info/LICENSE
moqpy-0.0.2.dist-info/METADATA
moqpy-0.0.2.dist-info/WHEEL
moqpy-0.0.2.dist-info/entry_points.txt
moqpy-0.0.2.dist-info/top_level.txt
moqpy-0.0.2.dist-info/RECORD
