Metadata-Version: 2.1
Name: moqpy
Version: 0.0.2
Summary: Extending unittest-mock with moq-like validators
Home-page: https://github.com/omlnaut/pymoq
Author: omlnaut
Author-email: oneironaut.oml@gmail.com
License: Apache Software License 2.0
Keywords: nbdev jupyter notebook python
Classifier: Development Status :: 4 - Beta
Classifier: Intended Audience :: Developers
Classifier: Natural Language :: English
Classifier: Programming Language :: Python :: 3.10
Classifier: License :: OSI Approved :: Apache Software License
Requires-Python: >=3.10
License-File: LICENSE
Provides-Extra: dev
